.gitignore
MANIFEST.in
README.rst
setup.py
coop_bar/__init__.py
coop_bar/bar.py
coop_bar/settings.py
coop_bar/urls.py
coop_bar/utils.py
coop_bar.egg-info/PKG-INFO
coop_bar.egg-info/SOURCES.txt
coop_bar.egg-info/dependency_links.txt
coop_bar.egg-info/not-zip-safe
coop_bar.egg-info/top_level.txt
coop_bar/static/css/coop_bar.css
coop_bar/static/fugue/abacus.png
coop_bar/static/fugue/acorn.png
coop_bar/static/fugue/address-book--arrow.png
coop_bar/static/fugue/address-book--exclamation.png
coop_bar/static/fugue/address-book--minus.png
coop_bar/static/fugue/address-book--pencil.png
coop_bar/static/fugue/address-book--plus.png
coop_bar/static/fugue/address-book-blue.png
coop_bar/static/fugue/address-book-open.png
coop_bar/static/fugue/address-book.png
coop_bar/static/fugue/alarm-clock--arrow.png
coop_bar/static/fugue/alarm-clock--exclamation.png
coop_bar/static/fugue/alarm-clock--minus.png
coop_bar/static/fugue/alarm-clock--pencil.png
coop_bar/static/fugue/alarm-clock--plus.png
coop_bar/static/fugue/alarm-clock-blue.png
coop_bar/static/fugue/alarm-clock-select-remain.png
coop_bar/static/fugue/alarm-clock-select.png
coop_bar/static/fugue/alarm-clock.png
coop_bar/static/fugue/anchor.png
coop_bar/static/fugue/android.png
coop_bar/static/fugue/animal-dog.png
coop_bar/static/fugue/animal-monkey-sulky.png
coop_bar/static/fugue/animal-monkey.png
coop_bar/static/fugue/animal-penguin.png
coop_bar/static/fugue/animal.png
coop_bar/static/fugue/application--arrow.png
coop_bar/static/fugue/application--exclamation.png
coop_bar/static/fugue/application--minus.png
coop_bar/static/fugue/application--pencil.png
coop_bar/static/fugue/application--plus.png
coop_bar/static/fugue/application-ab.png
coop_bar/static/fugue/application-block.png
coop_bar/static/fugue/application-blog.png
coop_bar/static/fugue/application-blue.png
coop_bar/static/fugue/application-browser.png
coop_bar/static/fugue/application-detail.png
coop_bar/static/fugue/application-dialog.png
coop_bar/static/fugue/application-dock-090.png
coop_bar/static/fugue/application-dock-180.png
coop_bar/static/fugue/application-dock-270.png
coop_bar/static/fugue/application-dock-tab.png
