Metadata-Version: 1.0
Name: coop-bar
Version: 0.4.6
Summary: Pluggable admin bar system , works well with coop-cms
Home-page: https://github.com/quinode/coop-bar/
Author: Luc Jean
Author-email: ljean@apidev.fr
License: BSD
Download-URL: https://github.com/quinode/coop-bar/tarball/master
Platform: UNKNOWN
Classifier: Development Status :: 4 - Beta
Classifier: Environment :: Web Environment
Classifier: Intended Audience :: Developers
Classifier: License :: OSI Approved :: BSD License
Classifier: Operating System :: OS Independent
Classifier: Programming Language :: Python
Classifier: Framework :: Django
Classifier: Natural Language :: English
Classifier: Natural Language :: French
Classifier: Topic :: Internet :: WWW/HTTP :: Dynamic Content
Classifier: Topic :: Internet :: WWW/HTTP :: WSGI :: Application
